napari_blender/__init__.py
napari_blender/_reader.py
napari_blender/_widget.py
napari_blender/_writer.py
napari_blender/napari.yaml
napari_blender/__pycache__/__init__.cpython-310.pyc
napari_blender/__pycache__/_reader.cpython-310.pyc
napari_blender/__pycache__/_sample_data.cpython-310.pyc
napari_blender/__pycache__/_widget.cpython-310.pyc
napari_blender/__pycache__/_writer.cpython-310.pyc
scenes/render_scene.blend
scripts/boolean_ops.py
scripts/compare.py
scripts/enums.py
scripts/interface.py
scripts/lineage.py
scripts/material.py
scripts/metrics.py
scripts/mode.py
scripts/object_helper.py
scripts/parse.py
scripts/rename.py
scripts/render.py
scripts/scene_helper.py
scripts/shapekey.py
scripts/trackmate.py
scripts/__pycache__/boolean_ops.cpython-310.pyc
scripts/__pycache__/compare.cpython-310.pyc
scripts/__pycache__/enums.cpython-310.pyc
scripts/__pycache__/interface.cpython-310.pyc
scripts/__pycache__/lineage.cpython-310.pyc
scripts/__pycache__/material.cpython-310.pyc
scripts/__pycache__/metrics.cpython-310.pyc
scripts/__pycache__/mode.cpython-310.pyc
scripts/__pycache__/object_helper.cpython-310.pyc
scripts/__pycache__/parse.cpython-310.pyc
scripts/__pycache__/rename.cpython-310.pyc
scripts/__pycache__/render.cpython-310.pyc
scripts/__pycache__/scene_helper.cpython-310.pyc
scripts/__pycache__/shapekey.cpython-310.pyc
scripts/__pycache__/shrinkwrap_animator.cpython-310.pyc
scripts/__pycache__/trackmate.cpython-310.pyc
napari_blender-1.0.1.dist-info/LICENSE
napari_blender-1.0.1.dist-info/METADATA
napari_blender-1.0.1.dist-info/WHEEL
napari_blender-1.0.1.dist-info/entry_points.txt
napari_blender-1.0.1.dist-info/top_level.txt
napari_blender-1.0.1.dist-info/RECORD
