Metadata-Version: 2.1
Name: napari-blender
Version: 1.0.1
Summary: A plug-in to help visualize and analyze organoid segmentation using Blender
Author-email: "Krijn H. van der Steen" <k.h.vandersteen@gmail.com>
License: 
Project-URL: Bug Tracker, https://github.com/Living-Technologies/napari-blender/issues
Project-URL: Documentation, https://living-technologies.github.io/napari-blender/index.html
Project-URL: Source Code, https://github.com/Living-Technologies/napari-blender
Project-URL: User Support, https://github.com/Living-Technologies/napari-blender/issues
Classifier: Development Status :: 3 - Alpha
Classifier: Framework :: napari
Classifier: Intended Audience :: Developers
Classifier: License :: OSI Approved :: Mozilla Public License 2.0 (MPL 2.0)
Classifier: Operating System :: OS Independent
Classifier: Programming Language :: Python
Classifier: Programming Language :: Python :: 3.10
Classifier: Topic :: Scientific/Engineering :: Image Processing
Requires-Python: >=3.10
License-File: LICENSE
Requires-Dist: numpy
Requires-Dist: magicgui
Requires-Dist: qtpy
Requires-Dist: scikit-image
Requires-Dist: napari-video
Requires-Dist: tifffile
Requires-Dist: bpy >=4.0.0
Requires-Dist: trimesh
Requires-Dist: opencv-python
Requires-Dist: scipy
Requires-Dist: pathlib
Requires-Dist: mathutils
Requires-Dist: pandas
